Metadata-Version: 2.1
Name: rclonedeobscure
Version: 1.1
Summary: A simple script to decrypt obscured/encrypted passwords from rclone
Home-page: https://github.com/maaaaz/rclonedeobscure
Author: Thomas D.
Author-email: tdebize@mail.com
License: MIT
Keywords: rclone deobscure obscure encrypt decrypt password
Classifier: Topic :: Security
Classifier: Development Status :: 5 - Production/Stable
Classifier: Intended Audience :: Information Technology
Classifier: Programming Language :: Python :: 3
Classifier: License :: OSI Approved :: MIT License
Requires-Python: >=3
